{"name":"Tags","body":"# Tags\r\n\r\nA Ruby object that acts like a set of tags.\r\n\r\n## Examples\r\n\r\n``` ruby\r\ntags = Tags.new(\"one, two, three\")\r\n\r\ntags - Tags.new(\"one, three\")\r\n# Tags.new(\"two\")\r\n\r\ntags + Tags.new(\"three, four, five\")\r\n# Tags.new(\"one, two, three, four, five\")\r\n\r\ntags.to_s\r\n# \"one, two, three\"\r\n\r\ntags.to_a\r\n# [\"one\", \"two\", \"three\"]\r\n\r\n# see the tests for more examples\r\n```","tagline":"A Ruby object with the behavior of a list of tags.","google":"","note":"Don't delete this file! It's used internally to help with page regeneration."}